file_attributes/__init__.py
file_attributes/file_attributes.py
file_attributes-1.0.0.dist-info/LICENSE
file_attributes-1.0.0.dist-info/METADATA
file_attributes-1.0.0.dist-info/WHEEL
file_attributes-1.0.0.dist-info/top_level.txt
file_attributes-1.0.0.dist-info/RECORD
