Metadata-Version: 2.2
Name: file_attributes
Version: 1.0.0
Summary: A Python package to get file attributes
Author-email: Xiaoming Zhou <xiaomingzhou958@baidu.com>
Project-URL: Homepage, https://github.com/xmz958/fileattributes
Project-URL: Documentation, https://github.com/xmz958/fileattributes
Classifier: Programming Language :: Python :: 3
Classifier: Operating System :: OS Independent
Requires-Python: >=3.8
License-File: LICENSE
